l2l/__init__.py
l2l/constants.py
l2l/errors.py
l2l/lane.py
l2l/mock.py
l2l/primary_lane.py
l2l/subscriber.py
l2l/types.py
l2l/utils.py
lane2lane-1.11.0.dist-info/licenses/LICENSE
lane2lane-1.11.0.dist-info/METADATA
lane2lane-1.11.0.dist-info/WHEEL
lane2lane-1.11.0.dist-info/top_level.txt
lane2lane-1.11.0.dist-info/RECORD
