Metadata-Version: 2.4
Name: lane2lane
Version: 1.11.0
Summary: A Python library for creating flexible, chainable, and prioritized processing pipelines.
Author: Talisik Team
Platform: unix
Platform: linux
Platform: osx
Platform: cygwin
Platform: win32
Classifier: Programming Language :: Python :: 3
Classifier: Programming Language :: Python :: 3 :: Only
Classifier: Programming Language :: Python :: 3.8
Classifier: Programming Language :: Python :: 3.9
Classifier: Programming Language :: Python :: 3.10
Classifier: Programming Language :: Python :: 3.11
Classifier: Programming Language :: Python :: 3.12
Requires-Python: >=3.6
License-File: LICENSE
Requires-Dist: fun-things
Requires-Dist: loguru
Requires-Dist: simple-chalk
Dynamic: license-file
